passwords.py
password_state_client-1.0.0.dist-info/WHEEL
password_state_client-1.0.0.dist-info/METADATA
password_state_client-1.0.0.dist-info/RECORD
