Metadata-Version: 2.1
Name: password_state_client
Version: 1.0.0
Summary: A package to retrieve passwords from the Passwordstate API
Author-email: Ryan Semmler <rsemmle@ncsu.edu>
Requires-Python: >=3.6
Classifier: Programming Language :: Python :: 3
Classifier: Operating System :: OS Independent
Requires-Dist: requests
Project-URL: Homepage, https://github.com/ncstate-sat/passwords
